ecoledirect/__init__.py
ecoledirect-4.0.0.dist-info/METADATA
ecoledirect-4.0.0.dist-info/WHEEL
ecoledirect-4.0.0.dist-info/top_level.txt
ecoledirect-4.0.0.dist-info/RECORD
