Metadata-Version: 2.1
Name: ecoledirect
Version: 4.0.0
Summary: With this package you can get the data from the website www.ecoledirect.com.
Home-page: https://github.com/Snowy-27/EcoleDirect
Author: Dan Habib
Author-email: dan.habib@yahoo.fr
License: unlicense
Platform: UNKNOWN
